Metadata-Version: 2.1
Name: odoo-addon-pms_l10n_es
Version: 16.0.2.0.0.1
Summary: PMS Spanish Adaptation
Home-page: https://github.com/OCA/pms
Author: Commit [Sun], Odoo Community Association (OCA)
Author-email: support@odoo-community.org
License: AGPL-3
Classifier: Programming Language :: Python
Classifier: Framework :: Odoo
Classifier: Framework :: Odoo :: 16.0
Classifier: License :: OSI Approved :: GNU Affero General Public License v3
Requires-Python: >=3.10
Requires-Dist: bs4
Requires-Dist: odoo-addon-base-iso3166<16.1dev,>=16.0dev
Requires-Dist: odoo-addon-l10n-es-aeat<16.1dev,>=16.0dev
Requires-Dist: odoo-addon-partner-contact-birthdate<16.1dev,>=16.0dev
Requires-Dist: odoo-addon-partner-contact-gender<16.1dev,>=16.0dev
Requires-Dist: odoo-addon-partner-contact-nationality<16.1dev,>=16.0dev
Requires-Dist: odoo-addon-partner-firstname<16.1dev,>=16.0dev
Requires-Dist: odoo-addon-partner-second-lastname<16.1dev,>=16.0dev
Requires-Dist: odoo-addon-pms<16.1dev,>=16.0dev
Requires-Dist: odoo-addon-pms-partner-identification<16.1dev,>=16.0dev
Requires-Dist: odoo-addon-pms-partner-second-lastname<16.1dev,>=16.0dev
Requires-Dist: odoo-addon-queue-job<16.1dev,>=16.0dev
Requires-Dist: odoo<16.1dev,>=16.0a
Requires-Dist: openupgradelib
Requires-Dist: pycountry
